grow_recipe/__init__.py
grow_recipe/constants.py
grow_recipe/grow-recipe.xsd
grow_recipe/schema.py
grow_recipe/query/__init__.py
grow_recipe/query/find_metric_value.py
grow_recipe/query/get_grow_stage.py
grow_recipe-0.8.0.dist-info/LICENSE
grow_recipe-0.8.0.dist-info/METADATA
grow_recipe-0.8.0.dist-info/WHEEL
grow_recipe-0.8.0.dist-info/top_level.txt
grow_recipe-0.8.0.dist-info/RECORD
